LICENSE
MANIFEST.in
README.rst
VERSION
requirements.txt
setup.cfg
setup.py
src/jsobj/__init__.py
src/novo_jsobj.egg-info/PKG-INFO
src/novo_jsobj.egg-info/SOURCES.txt
src/novo_jsobj.egg-info/dependency_links.txt
src/novo_jsobj.egg-info/top_level.txt