Metadata-Version: 1.1
Name: novo-jsobj
Version: 0.0.1
Summary: Utility class around dict for easier use
Home-page: https://github.com/novopl/jsobj
Author: Mateusz 'novo' Klos
Author-email: novopl@gmail.com
License: MIT
Platform: UNKNOWN
Classifier: Development Status :: 3 - Alpha
Classifier: Topic :: Utilities
Classifier: Intended Audience :: Developers
Classifier: Programming Language :: Python
Classifier: License :: OSI Approved :: MIT License
